iatoolkit/__init__.py
iatoolkit/base_company.py
iatoolkit/cli_commands.py
iatoolkit/company_registry.py
iatoolkit/core.py
iatoolkit/common/__init__.py
iatoolkit/common/exceptions.py
iatoolkit/common/model_registry.py
iatoolkit/common/routes.py
iatoolkit/common/session_manager.py
iatoolkit/common/util.py
iatoolkit/common/interfaces/__init__.py
iatoolkit/common/interfaces/asset_storage.py
iatoolkit/common/interfaces/database_provider.py
iatoolkit/infra/__init__.py
iatoolkit/infra/brevo_mail_app.py
iatoolkit/infra/call_service.py
iatoolkit/infra/google_chat_app.py
iatoolkit/infra/inference_embeddings_client.py
iatoolkit/infra/inference_handler.py
iatoolkit/infra/jina_embeddings_client.py
iatoolkit/infra/llm_proxy.py
iatoolkit/infra/llm_response.py
iatoolkit/infra/redis_session_manager.py
iatoolkit/infra/connectors/__init__.py
iatoolkit/infra/connectors/file_connector.py
iatoolkit/infra/connectors/file_connector_factory.py
iatoolkit/infra/connectors/google_cloud_storage_connector.py
iatoolkit/infra/connectors/google_drive_connector.py
iatoolkit/infra/connectors/local_file_connector.py
iatoolkit/infra/connectors/s3_connector.py
iatoolkit/infra/llm_providers/__init__.py
iatoolkit/infra/llm_providers/deepseek_adapter.py
iatoolkit/infra/llm_providers/gemini_adapter.py
iatoolkit/infra/llm_providers/openai_adapter.py
iatoolkit/locales/en.yaml
iatoolkit/locales/es.yaml
iatoolkit/repositories/__init__.py
iatoolkit/repositories/database_manager.py
iatoolkit/repositories/document_repo.py
iatoolkit/repositories/filesystem_asset_repository.py
iatoolkit/repositories/llm_query_repo.py
iatoolkit/repositories/models.py
iatoolkit/repositories/profile_repo.py
iatoolkit/repositories/vs_repo.py
iatoolkit/services/__init__.py
iatoolkit/services/auth_service.py
iatoolkit/services/benchmark_service.py
iatoolkit/services/branding_service.py
iatoolkit/services/company_context_service.py
iatoolkit/services/configuration_service.py
iatoolkit/services/context_builder_service.py
iatoolkit-1.34.6.dist-info/licenses/LICENSE
iatoolkit-1.34.6.dist-info/licenses/LICENSE_COMMUNITY.md
iatoolkit-1.34.6.dist-info/METADATA
iatoolkit-1.34.6.dist-info/WHEEL
iatoolkit-1.34.6.dist-info/top_level.txt
iatoolkit-1.34.6.dist-info/RECORD
