Metadata-Version: 2.4
Name: iatoolkit
Version: 1.34.6
Summary: IAToolkit
Author: Fernando Libedinsky
License-Expression: MIT
Requires-Python: >=3.12
License-File: LICENSE
License-File: LICENSE_COMMUNITY.md
Requires-Dist: bcrypt==4.2.1
Requires-Dist: boto3==1.36.22
Requires-Dist: botocore==1.36.22
Requires-Dist: build==1.2.2.post1
Requires-Dist: click==8.1.8
Requires-Dist: cryptography==44.0.3
Requires-Dist: Flask==3.1.0
Requires-Dist: Flask-Bcrypt==1.0.1
Requires-Dist: flask-cors==6.0.0
Requires-Dist: Flask-Injector==0.15.0
Requires-Dist: Flask-Session==0.8.0
Requires-Dist: flatbuffers==24.3.25
Requires-Dist: google-ai-generativelanguage==0.6.15
Requires-Dist: google-api-core==2.24.1
Requires-Dist: google-api-python-client==2.161.0
Requires-Dist: google-auth>=2.46.0
Requires-Dist: google-auth-httplib2==0.2.0
Requires-Dist: google-auth-oauthlib==1.2.1
Requires-Dist: google-cloud-core==2.4.1
Requires-Dist: google-cloud-storage==3.0.0
Requires-Dist: google-crc32c==1.6.0
Requires-Dist: google-genai==1.57.0
Requires-Dist: google-resumable-media==2.7.2
Requires-Dist: googleapis-common-protos==1.66.0
Requires-Dist: gunicorn==23.0.0
Requires-Dist: h11==0.14.0
Requires-Dist: httpcore==1.0.7
Requires-Dist: httplib2==0.22.0
Requires-Dist: httptools==0.6.4
Requires-Dist: httpx<1.0.0,>=0.28.1
Requires-Dist: httpx-sse==0.4.0
Requires-Dist: huggingface-hub==0.16.4
Requires-Dist: humanfriendly==10.0
Requires-Dist: idna==3.10
Requires-Dist: injector==0.22.0
Requires-Dist: Jinja2==3.1.5
Requires-Dist: langchain==0.3.19
Requires-Dist: langchain-core==0.3.35
Requires-Dist: langchain-text-splitters==0.3.6
Requires-Dist: markdown2==2.5.3
Requires-Dist: openai==2.8.1
Requires-Dist: openpyxl==3.1.5
Requires-Dist: pandas==2.3.1
Requires-Dist: pgvector==0.3.6
Requires-Dist: pillow==11.0.0
Requires-Dist: psutil==7.0.0
Requires-Dist: psycopg2-binary==2.9.10
Requires-Dist: PyJWT==2.10.1
Requires-Dist: PyMuPDF==1.25.0
Requires-Dist: python-dotenv==1.0.1
Requires-Dist: pytest==8.3.4
Requires-Dist: pytest-cov==5.0.0
Requires-Dist: pytest-mock==3.14.0
Requires-Dist: python-dateutil==2.9.0.post0
Requires-Dist: python-docx==1.1.2
Requires-Dist: pytesseract==0.3.13
Requires-Dist: pytz==2025.2
Requires-Dist: PyYAML==6.0.2
Requires-Dist: redis==5.2.1
Requires-Dist: regex==2024.11.6
Requires-Dist: requests==2.32.3
Requires-Dist: requests-oauthlib==2.0.0
Requires-Dist: requests-toolbelt==1.0.0
Requires-Dist: s3transfer==0.11.2
Requires-Dist: sib-api-v3-sdk==7.6.0
Requires-Dist: SQLAlchemy==2.0.36
Requires-Dist: tiktoken==0.8.0
Requires-Dist: tokenizers==0.21.0
Requires-Dist: websocket-client==1.8.0
Requires-Dist: websockets==14.1
Requires-Dist: Werkzeug==3.1.3
Requires-Dist: pyjwt[crypto]>=2.8.0
Dynamic: license-file
